hdict/__init__.py
hdict/abs/__init__.py
hdict/content/__init__.py
hdict/content/argument/__init__.py
hdict/content/argument/apply.py
hdict/content/argument/aux_apply.py
hdict/content/argument/default.py
hdict/content/argument/entry.py
hdict/content/argument/field.py
hdict/content/argument/sample.py
hdict/content/aux_value.py
hdict/content/entry/__init__.py
hdict/content/entry/aux_closure.py
hdict/content/entry/cached.py
hdict/content/entry/closure.py
hdict/content/entry/subvalue.py
hdict/content/entry/wrapper.py
hdict/content/value.py
hdict/data/__init__.py
hdict/data/aux_frozendict.py
hdict/data/empty_.py
hdict/data/frozenhdict.py
hdict/data/hdict_.py
hdict/data/self_.py
hdict/dataset/__init__.py
hdict/dataset/dataset.py
hdict/dataset/pandas_handling.py
hdict/expression/__init__.py
hdict/expression/expr.py
hdict/expression/step/__init__.py
hdict/expression/step/applyout.py
hdict/expression/step/cache.py
hdict/expression/step/edict.py
hdict/expression/step/step.py
hdict/persistence/__init__.py
hdict/persistence/stored.py
hdict/text/__init__.py
hdict/text/customjson.py
hdict-2.250313.2.dist-info/LICENSE
hdict-2.250313.2.dist-info/METADATA
hdict-2.250313.2.dist-info/WHEEL
hdict-2.250313.2.dist-info/RECORD
