Metadata-Version: 2.3
Name: hdict
Version: 2.250313.2
Summary: A versatile dictionary based on a novel paradigm useful for computing, caching, experiments, distributed data, among others.
License: GPLv3
Author: davips
Author-email: dpsabc@gmail.com
Requires-Python: >=3.10,<4.0
Classifier: License :: Other/Proprietary License
Classifier: Programming Language :: Python :: 3
Classifier: Programming Language :: Python :: 3.10
Classifier: Programming Language :: Python :: 3.11
Classifier: Programming Language :: Python :: 3.12
Classifier: Programming Language :: Python :: 3.13
Provides-Extra: full
Requires-Dist: blake3 (>=1.0.4,<2.0.0)
Requires-Dist: hosh (>=3.230705.5,<4.0.0)
Requires-Dist: indexed (>=1.3.0,<2.0.0)
Requires-Dist: lange (>=1.230203.2,<2.0.0)
Requires-Dist: liac-arff (>=2.5.0,<3.0.0) ; extra == "full"
Requires-Dist: lz4 (>=4.3.2,<5.0.0) ; extra == "full"
Requires-Dist: pandas (>=2.0.0,<3.0.0) ; extra == "full"
Requires-Dist: safeserializer (>=0.230202.1,<0.230203.0) ; extra == "full"
Requires-Dist: scikit-learn (>=1.2.2,<2.0.0) ; extra == "full"
Requires-Dist: shelchemy (>=0.220906.3,<0.220907.0) ; extra == "full"
